pcr2echo/__init__.py
pcr2echo/pcr2echo.py
pcr2echo-1.0.5.dist-info/METADATA
pcr2echo-1.0.5.dist-info/WHEEL
pcr2echo-1.0.5.dist-info/licenses/LICENSE
pcr2echo-1.0.5.dist-info/RECORD
